[
  {
    "ContainingType": "game_zone_api.Controllers.GamersController",
    "Method": "GetGamers",
    "RelativePath": "api/Gamers",
    "HttpMethod": "GET",
    "IsController": true,
    "Order": 0,
    "Parameters": [],
    "ReturnTypes": [
      {
        "Type": "System.Collections.Generic.IEnumerable\u00601[[game_zone_api.Models.Gamer, game-zone-api, Version=1.0.0.0, Culture=neutral, PublicKeyToken=null]]",
        "MediaTypes": [
          "text/plain",
          "application/json",
          "text/json"
        ],
        "StatusCode": 200
      }
    ]
  },
  {
    "ContainingType": "game_zone_api.Controllers.GamersController",
    "Method": "PostGamer",
    "RelativePath": "api/Gamers",
    "HttpMethod": "POST",
    "IsController": true,
    "Order": 0,
    "Parameters": [
      {
        "Name": "gamer",
        "Type": "game_zone_api.Models.Gamer",
        "IsRequired": true
      }
    ],
    "ReturnTypes": [
      {
        "Type": "game_zone_api.Models.Gamer",
        "MediaTypes": [
          "text/plain",
          "application/json",
          "text/json"
        ],
        "StatusCode": 200
      }
    ]
  },
  {
    "ContainingType": "game_zone_api.Controllers.GamersController",
    "Method": "Login",
    "RelativePath": "api/Gamers/login",
    "HttpMethod": "POST",
    "IsController": true,
    "Order": 0,
    "Parameters": [
      {
        "Name": "gamer",
        "Type": "game_zone_api.Models.Login",
        "IsRequired": true
      }
    ],
    "ReturnTypes": []
  },
  {
    "ContainingType": "game_zone_api.Controllers.ScoresController",
    "Method": "GetScores",
    "RelativePath": "api/Scores",
    "HttpMethod": "GET",
    "IsController": true,
    "Order": 0,
    "Parameters": [],
    "ReturnTypes": [
      {
        "Type": "System.Collections.Generic.IEnumerable\u00601[[game_zone_api.Models.Score, game-zone-api, Version=1.0.0.0, Culture=neutral, PublicKeyToken=null]]",
        "MediaTypes": [
          "text/plain",
          "application/json",
          "text/json"
        ],
        "StatusCode": 200
      }
    ]
  },
  {
    "ContainingType": "game_zone_api.Controllers.ScoresController",
    "Method": "PostScore",
    "RelativePath": "api/Scores",
    "HttpMethod": "POST",
    "IsController": true,
    "Order": 0,
    "Parameters": [
      {
        "Name": "score",
        "Type": "game_zone_api.Models.Score",
        "IsRequired": true
      }
    ],
    "ReturnTypes": [
      {
        "Type": "game_zone_api.Models.Score",
        "MediaTypes": [
          "text/plain",
          "application/json",
          "text/json"
        ],
        "StatusCode": 200
      }
    ]
  },
  {
    "ContainingType": "game_zone_api.Controllers.ScoresController",
    "Method": "GetScore",
    "RelativePath": "api/Scores/{id}",
    "HttpMethod": "GET",
    "IsController": true,
    "Order": 0,
    "Parameters": [
      {
        "Name": "id",
        "Type": "System.Int32",
        "IsRequired": true
      }
    ],
    "ReturnTypes": [
      {
        "Type": "System.Collections.Generic.List\u00601[[game_zone_api.Models.Score, game-zone-api, Version=1.0.0.0, Culture=neutral, PublicKeyToken=null]]",
        "MediaTypes": [
          "text/plain",
          "application/json",
          "text/json"
        ],
        "StatusCode": 200
      }
    ]
  },
  {
    "ContainingType": "game_zone_api.Controllers.ScoresController",
    "Method": "PutScore",
    "RelativePath": "api/Scores/{id}",
    "HttpMethod": "PUT",
    "IsController": true,
    "Order": 0,
    "Parameters": [
      {
        "Name": "id",
        "Type": "System.Int32",
        "IsRequired": true
      },
      {
        "Name": "score",
        "Type": "game_zone_api.Models.Score",
        "IsRequired": true
      }
    ],
    "ReturnTypes": []
  },
  {
    "ContainingType": "game_zone_api.Controllers.ScoresController",
    "Method": "DeleteScore",
    "RelativePath": "api/Scores/{id}",
    "HttpMethod": "DELETE",
    "IsController": true,
    "Order": 0,
    "Parameters": [
      {
        "Name": "id",
        "Type": "System.Int32",
        "IsRequired": true
      }
    ],
    "ReturnTypes": []
  }
]